convection/shared/__init__.py
convection/shared/config.py
convection/shared/convection-sm-commands.toml
convection/shared/exceptions.py
convection/shared/functions.py
convection/shared/specker_static.py
convection/shared/objects/__init__.py
convection/shared/objects/group.py
convection/shared/objects/instance.py
convection/shared/objects/metadata.py
convection/shared/objects/object.py
convection/shared/objects/plugin.py
convection/shared/objects/plugin_metadata.py
convection/shared/objects/target.py
convection/shared/objects/targetable.py
convection/shared/objects/plugins/access.py
convection/shared/objects/plugins/action.py
convection/shared/objects/plugins/connector.py
convection/shared/objects/plugins/secret.py
convection/shared/specs/anyitem.spec
convection/shared/specs/argmap.command.spec
convection/shared/specs/global.reporting.log.spec
convection/shared/specs/global.reporting.spec
convection/shared/specs/global.secrets.client.auth.spec
convection/shared/specs/global.secrets.client.network.spec
convection/shared/specs/global.secrets.client.spec
convection/shared/specs/global.secrets.spec
convection/shared/specs/global.spec
convection/shared/specs/group.spec
convection/shared/specs/metadata.plugin.spec
convection/shared/specs/metadata.spec
convection/shared/specs/plugin.access.spec
convection/shared/specs/plugin.action.spec
convection/shared/specs/plugin.connector.spec
convection/shared/specs/plugin.spec
convection/shared/specs/root.spec
convection/shared/specs/target.spec
convection_shared-1.0.0.dist-info/LICENSE.md
convection_shared-1.0.0.dist-info/METADATA
convection_shared-1.0.0.dist-info/WHEEL
convection_shared-1.0.0.dist-info/top_level.txt
convection_shared-1.0.0.dist-info/RECORD
