Metadata-Version: 2.1
Name: convection-shared
Version: 1.0.0
Summary: Convection Shared Library
Author-email: AccidentallyTheCable <cableninja@cableninja.net>
License: GPLv3
Project-URL: Homepage, https://gitlab.com/accidentallythecable-public/convection-suite/convection-shared/
Project-URL: Bug Tracker, https://gitlab.com/accidentallythecable-public/convection-suite/convection-shared/issues
Classifier: Programming Language :: Python :: 3
Classifier: License :: OSI Approved :: GNU General Public License v3 (GPLv3)
Classifier: Environment :: Console
Classifier: Operating System :: OS Independent
Classifier: Topic :: System :: Installation/Setup
Classifier: Topic :: System :: Systems Administration
Classifier: Topic :: Utilities
Requires-Python: >=3.9
License-File: LICENSE.md
Requires-Dist: atckit <2.0,>=1.0
Requires-Dist: specker <2.0,>=1.0
Requires-Dist: argstruct <2.0,>=1.0
Requires-Dist: deepmerge <=1.2.0,>=1.1.0
Requires-Dist: tomlkit <1.0
Requires-Dist: PyYAML <7.0
Requires-Dist: tabulate <1.0
Requires-Dist: types-tabulate <1.0
